LICENSE.txt
MANIFEST.in
README.txt
setup.py
top/__init__.py
top/api/__init__.py
top/api/base.py
top/api/rest/AlibabaAliqinFcFlowChargeProvinceRequest.py
top/api/rest/AlibabaAliqinFcFlowChargeRequest.py
top/api/rest/AlibabaAliqinFcFlowGradeRequest.py
top/api/rest/AlibabaAliqinFcFlowQueryRequest.py
top/api/rest/AlibabaAliqinFcSmsNumQueryRequest.py
top/api/rest/AlibabaAliqinFcSmsNumSendRequest.py
top/api/rest/AlibabaAliqinFcTtsNumSinglecallRequest.py
top/api/rest/AlibabaAliqinFcVoiceNumDoublecallRequest.py
top/api/rest/AlibabaAliqinFcVoiceNumSinglecallRequest.py
top/api/rest/AppipGetRequest.py
top/api/rest/AreasGetRequest.py
top/api/rest/HttpdnsGetRequest.py
top/api/rest/KfcKeywordSearchRequest.py
top/api/rest/TimeGetRequest.py
top/api/rest/TopAuthTokenCreateRequest.py
top/api/rest/TopAuthTokenRefreshRequest.py
top/api/rest/TopIpoutGetRequest.py
top/api/rest/TopSecretGetRequest.py
top/api/rest/TopatsResultGetRequest.py
top/api/rest/TopatsTaskDeleteRequest.py
top/api/rest/__init__.py
zhj_top.egg-info/PKG-INFO
zhj_top.egg-info/SOURCES.txt
zhj_top.egg-info/dependency_links.txt
zhj_top.egg-info/top_level.txt