Metadata-Version: 1.1
Name: zhj-top
Version: 1.0.0
Summary: taobao openapi interface
Home-page: https://pypi.python.org/pypi/zhj_top/
Author: taobao Team
Author-email: zhongjin616@foxmail.com
License: UNKNOWN
Keywords: taobao openapi
Platform: UNKNOWN
Classifier: Development Status :: 3 - Alpha
Classifier: Intended Audience :: Developers
Classifier: Topic :: Software Development :: Libraries :: Python Modules
Classifier: License :: OSI Approved :: MIT License
Classifier: Programming Language :: Python :: 2.7
